openrpa/OpenRPA.py
openrpa/__init__.py
openrpa-0.3.1.dist-info/LICENSE
openrpa-0.3.1.dist-info/WHEEL
openrpa-0.3.1.dist-info/METADATA
openrpa-0.3.1.dist-info/RECORD
